rewiringamerica_rem/__init__.py
rewiringamerica_rem/api/__init__.py
rewiringamerica_rem/api/building_profiler_api.py
rewiringamerica_rem/api/residential_electrification_model_api.py
rewiringamerica_rem/api_client.py
rewiringamerica_rem/api_response.py
rewiringamerica_rem/configuration.py
rewiringamerica_rem/exceptions.py
rewiringamerica_rem/models/__init__.py
rewiringamerica_rem/models/address_component_request.py
rewiringamerica_rem/models/building_features.py
rewiringamerica_rem/models/building_profile.py
rewiringamerica_rem/models/fuel_rate.py
rewiringamerica_rem/models/fuel_savings.py
rewiringamerica_rem/models/heating_fuel.py
rewiringamerica_rem/models/http_validation_error.py
rewiringamerica_rem/models/impact_metric.py
rewiringamerica_rem/models/metric_statistics.py
rewiringamerica_rem/models/quantity.py
rewiringamerica_rem/models/rem_profile_request.py
rewiringamerica_rem/models/result_fuel_type.py
rewiringamerica_rem/models/sampling_details.py
rewiringamerica_rem/models/savings.py
rewiringamerica_rem/models/supported_upgrade.py
rewiringamerica_rem/models/validation_error.py
rewiringamerica_rem/models/validation_error_loc_inner.py
rewiringamerica_rem/models/water_heater_fuel.py
rewiringamerica_rem/py.typed
rewiringamerica_rem/rest.py
rewiringamerica_rem-1.3.2.dist-info/METADATA
rewiringamerica_rem-1.3.2.dist-info/WHEEL
rewiringamerica_rem-1.3.2.dist-info/RECORD
