Metadata-Version: 2.3
Name: rewiringamerica_rem
Version: 1.3.2
Summary: Residential Electrification Model API
License: Apache 2.0
Keywords: OpenAPI,OpenAPI-Generator,Residential Electrification Model API
Author: Rewiring America
Author-email: datascience@rewiringamerica.org
Requires-Python: >=3.8,<4.0
Classifier: License :: Other/Proprietary License
Classifier: Programming Language :: Python :: 3
Classifier: Programming Language :: Python :: 3.8
Classifier: Programming Language :: Python :: 3.9
Classifier: Programming Language :: Python :: 3.10
Classifier: Programming Language :: Python :: 3.11
Classifier: Programming Language :: Python :: 3.12
Classifier: Programming Language :: Python :: 3.13
Requires-Dist: pydantic (>=2)
Requires-Dist: python-dateutil (>=2.8.2)
Requires-Dist: typing-extensions (>=4.7.1)
Requires-Dist: urllib3 (>=1.25.3,<3.0.0)
Project-URL: Repository, https://github.com/rewiringamerica/ra-api-rem-py
